{
  "timestamp": "2025-08-02T23:59:16.719Z",
  "orders": {
    "total": 0,
    "completed": 0,
    "pending": 0,
    "processing": 0
  },
  "usbs": {
    "connected": 7,
    "empty": 1,
    "devices": [
      {
        "label": "316528",
        "size": "7.48 GB",
        "freeSpace": "3.98 GB",
        "isEmpty": false
      },
      {
        "label": "310229",
        "size": "29.28 GB",
        "freeSpace": "544 KB",
        "isEmpty": false
      },
      {
        "label": "320494",
        "size": "58.58 GB",
        "freeSpace": "1.62 GB",
        "isEmpty": false
      },
      {
        "label": "311875",
        "size": "58.58 GB",
        "freeSpace": "10.5 GB",
        "isEmpty": false
      },
      {
        "label": "315401",
        "size": "7.48 GB",
        "freeSpace": "5.08 GB",
        "isEmpty": false
      },
      {
        "label": "320909",
        "size": "7.48 GB",
        "freeSpace": "312 KB",
        "isEmpty": false
      },
      {
        "label": "313384",
        "size": "7.48 GB",
        "freeSpace": "7.48 GB",
        "isEmpty": true
      }
    ]
  },
  "revenue": {
    "total": 0,
    "average": 0
  }
}